{"cameraMode":{"drawMode":0,"name":"Shaded","section":"Shading Mode"},"sceneLighting":true,"audioPlay":false,"sceneViewState":{"m_AlwaysRefresh":false,"showFog":true,"showSkybox":true,"showFlares":true,"showImageEffects":true,"showParticleSystems":true,"showVisualEffectGraphs":true,"m_FxEnabled":true},"in2DMode":false,"pivot":{"x":-24.24036979675293,"y":4.303535461425781,"z":211.31900024414063},"rotation":{"x":-0.24384081363677979,"y":0.16416649520397187,"z":-0.04131998494267464,"w":-0.954972505569458},"size":110.93745422363281,"orthographic":true}